.editorconfig
.gitignore
CHANGELOG.md
Makefile
README.md
pyproject.toml
requirements-dev.txt
setup.cfg
setup.py
rmachine68k/__init__.py
rmachine68k/client.py
rmachine68k/server.py
rmachine68k/service.py
rmachine68k/tool.py
rmachine68k.egg-info/PKG-INFO
rmachine68k.egg-info/SOURCES.txt
rmachine68k.egg-info/dependency_links.txt
rmachine68k.egg-info/entry_points.txt
rmachine68k.egg-info/requires.txt
rmachine68k.egg-info/top_level.txt
test/conftest.py
test/pytest.ini
test/test_client.py