Metadata-Version: 2.4
Name: rmachine68k
Version: 0.1.0
Summary: Use a remote machine68k system emulator
Author-email: Christian Vogelgsang <chris@vogelgsang.org>
License-Expression: GPL-2.0-or-later
Keywords: AmigaOS,machine68k,vamos
Classifier: Development Status :: 4 - Beta
Classifier: Intended Audience :: Developers
Classifier: Programming Language :: Python
Classifier: Topic :: System :: Emulators
Requires-Python: >=3.9
Requires-Dist: machine68k
Requires-Dist: rpyc
